hf/convert/__init__.py
hf/convert/steps/__init__.py
hf/convert/steps/_base.py
hf/convert/steps/download.py
hf/convert/steps/first_frame.py
hf/convert/steps/jpg_to_webp.py
hf/convert/steps/minimize_mp4.py
hf/convert/steps/mp4_size.py
hf/convert/steps/mp4_to_webp.py
hf/convert/steps/upload_to_s3.py
hf_py_convert-0.2.1.dist-info/METADATA
hf_py_convert-0.2.1.dist-info/WHEEL
hf_py_convert-0.2.1.dist-info/RECORD
