Metadata-Version: 2.3
Name: hf-py-convert
Version: 0.2.1
Summary: 
Author: kuanysh-beisembayev
Author-email: kuanysh.beisembayev@gmail.com
Requires-Python: >=3.12,<4.0
Classifier: Programming Language :: Python :: 3
Classifier: Programming Language :: Python :: 3.12
Classifier: Programming Language :: Python :: 3.13
Requires-Dist: aiobotocore (>=2.22.0,<3.0.0)
Requires-Dist: ffmpeg-python (>=0.2.0,<0.3.0)
Requires-Dist: httpx (>=0.28.1,<0.29.0)
Requires-Dist: moviepy (>=2.2.1,<3.0.0)
Requires-Dist: pillow (>=11.2.1,<12.0.0)
